LICENSE
setup.py
django_freeperms.egg-info/PKG-INFO
django_freeperms.egg-info/SOURCES.txt
django_freeperms.egg-info/dependency_links.txt
django_freeperms.egg-info/not-zip-safe
django_freeperms.egg-info/top_level.txt
docs/freeperms.txt
freeperms/__init__.py
freeperms/base.py
freeperms/middleware.py