Metadata-Version: 1.0
Name: django-freeperms
Version: 0.1
Summary: Django middleware for enabling anonymous permissions
Home-page: http://pypi.python.org/pypi/django-freeperms
Author: Tamas Kemenczy
Author-email: tamas.kemenczy@gmail.com
License: BSD
Keywords: django middleware permissions auth
Platform: UNKNOWN
Classifier: Development Status :: 4 - Beta
Classifier: Environment :: Web Environment
Classifier: Framework :: Django
Classifier: Intended Audience :: Developers
Classifier: License :: OSI Approved :: BSD License
Classifier: Operating System :: OS Independent
Classifier: Programming Language :: Python
